{
  "properties": {
    "metadata": {
      "assignedBy": "github.com/hmcts/azure-policy"
    },
    "description": "Audit AKS Clusters which do not restrict FlexVolume drivers",
    "displayName": "AKS Restrict FlexVolume Drivers - (mg:CFT-Sandbox)",
    "enforcementMode": "Default",
    "notScopes": [],
    "parameters": {
      "effect": {
        "value": "Audit"
      },
      "allowedFlexVolumeDrivers": {
        "value": []
      }
    },
    "policyDefinitionId": "/providers/Microsoft.Authorization/policyDefinitions/f4a8fce0-2dd5-4c21-9a36-8f0ec809d663",
    "scope": "/providers/Microsoft.Management/managementGroups/CFT-Sandbox"
  },
  "type": "Microsoft.Authorization/policyAssignments",
  "id": "/providers/Microsoft.Management/managementGroups/CFT-Sandbox/providers/Microsoft.Authorization/policyAssignments/AKSLimitFlexVolDrv-sbox",
  "name": "AKSLimitFlexVolDrv-sbox",
  "location": "uksouth",
  "sku": {
    "name": "A0",
    "tier": "Free"
  }
}