{
  "properties": {
    "metadata": {
      "assignedBy": "github.com/hmcts/azure-policy"
    },
    "description": "Audit AKS containers using the 'latest' image tag.",
    "displayName": "AKS No Latest Image Tag (mg:CFT-Sandbox)",
    "enforcementMode": "Default",
    "nonComplianceMessages": [
      {
        "message": "Container images should not use the 'latest' tag."
      }
    ],
    "notScopes": [],
    "parameters": {
      "effect": {
        "value": "Audit"
      }
    },
    "policyDefinitionId": "/providers/Microsoft.Authorization/policyDefinitions/021f8078-41a0-40e6-81b6-c6597da9f3ee",
    "scope": "/providers/Microsoft.Management/managementGroups/CFT-Sandbox"
  },
  "type": "Microsoft.Authorization/policyAssignments",
  "id": "/providers/Microsoft.Management/managementGroups/CFT-Sandbox/providers/Microsoft.Authorization/policyAssignments/AKSNoLatestTag-sbox",
  "name": "AKSNoLatestTag-sbox",
  "location": "uksouth",
  "sku": {
    "name": "A0",
    "tier": "Free"
  }
}